{".class": "MypyFile", "_fullname": "modbusSlave", "is_partial_stub_package": false, "is_stub": false, "names": {".class": "SymbolTable", "Config": {".class": "SymbolTableNode", "kind": "Gdef", "node": {".class": "Var", "flags": ["is_suppressed_import", "is_ready"], "fullname": "modbusSlave.Config", "name": "Config", "type": {".class": "AnyType", "missing_import_name": "modbusSlave.Config", "source_any": null, "type_of_any": 3}}}, "ModbusSlave": {".class": "SymbolTableNode", "kind": "Gdef", "node": {".class": "TypeInfo", "_promote": null, "abstract_attributes": [], "bases": ["builtins.object"], "declared_metaclass": null, "defn": {".class": "ClassDef", "fullname": "modbusSlave.ModbusSlave", "name": "ModbusSlave", "type_vars": []}, "flags": [], "fullname": "modbusSlave.ModbusSlave", "metaclass_type": null, "metadata": {}, "module_name": "modbusSlave", "mro": ["modbusSlave.ModbusSlave", "builtins.object"], "names": {".class": "SymbolTable", "DE": {".class": "SymbolTableNode", "implicit": true, "kind": "Mdef", "node": {".class": "Var", "flags": [], "fullname": "modbusSlave.ModbusSlave.DE", "name": "DE", "type": {".class": "AnyType", "missing_import_name": null, "source_any": null, "type_of_any": 1}}}, "ID": {".class": "SymbolTableNode", "implicit": true, "kind": "Mdef", "node": {".class": "Var", "flags": [], "fullname": "modbusSlave.ModbusSlave.ID", "name": "ID", "type": {".class": "AnyType", "missing_import_name": null, "source_any": null, "type_of_any": 1}}}, "LOGGER": {".class": "SymbolTableNode", "implicit": true, "kind": "Mdef", "node": {".class": "Var", "flags": [], "fullname": "modbusSlave.ModbusSlave.LOGGER", "name": "LOGGER", "type": {".class": "AnyType", "missing_import_name": null, "source_any": null, "type_of_any": 1}}}, "__init__": {".class": "SymbolTableNode", "kind": "Mdef", "node": {".class": "FuncDef", "arg_kinds": [0, 0, 0, 0, 0, 0, 1], "arg_names": ["self", "baudrate", "wattmeter", "evse", "rfid", "config", "debug"], "flags": [], "fullname": "modbusSlave.ModbusSlave.__init__", "name": "__init__", "type": null}}, "config": {".class": "SymbolTableNode", "implicit": true, "kind": "Mdef", "node": {".class": "Var", "flags": [], "fullname": "modbusSlave.ModbusSlave.config", "name": "config", "type": {".class": "AnyType", "missing_import_name": null, "source_any": null, "type_of_any": 1}}}, "evse": {".class": "SymbolTableNode", "implicit": true, "kind": "Mdef", "node": {".class": "Var", "flags": [], "fullname": "modbusSlave.ModbusSlave.evse", "name": "evse", "type": {".class": "AnyType", "missing_import_name": null, "source_any": null, "type_of_any": 1}}}, "modbusCheckProccess": {".class": "SymbolTableNode", "kind": "Mdef", "node": {".class": "FuncDef", "arg_kinds": [0, 0], "arg_names": ["self", "receiveData"], "flags": [], "fullname": "modbusSlave.ModbusSlave.modbusCheckProccess", "name": "modbusCheckProccess", "type": null}}, "modbusClient": {".class": "SymbolTableNode", "implicit": true, "kind": "Mdef", "node": {".class": "Var", "flags": [], "fullname": "modbusSlave.ModbusSlave.modbusClient", "name": "modbusClient", "type": {".class": "AnyType", "missing_import_name": null, "source_any": null, "type_of_any": 1}}}, "proccessEspData": {".class": "SymbolTableNode", "kind": "Mdef", "node": {".class": "FuncDef", "arg_kinds": [0, 0, 0, 0, 0], "arg_names": ["self", "fce", "length", "reg", "receiveData"], "flags": [], "fullname": "modbusSlave.ModbusSlave.proccessEspData", "name": "proccessEspData", "type": null}}, "proccessEvseData": {".class": "SymbolTableNode", "kind": "Mdef", "node": {".class": "FuncDef", "arg_kinds": [0, 0, 0, 0], "arg_names": ["self", "fce", "length", "reg"], "flags": [], "fullname": "modbusSlave.ModbusSlave.proccessEvseData", "name": "proccessEvseData", "type": null}}, "proccessRfidData": {".class": "SymbolTableNode", "kind": "Mdef", "node": {".class": "FuncDef", "arg_kinds": [0, 0, 0, 0], "arg_names": ["self", "fce", "length", "reg"], "flags": [], "fullname": "modbusSlave.ModbusSlave.proccessRfidData", "name": "proccessRfidData", "type": null}}, "proccessWattmeterData": {".class": "SymbolTableNode", "kind": "Mdef", "node": {".class": "FuncDef", "arg_kinds": [0, 0, 0, 0], "arg_names": ["self", "fce", "length", "reg"], "flags": [], "fullname": "modbusSlave.ModbusSlave.proccessWattmeterData", "name": "proccessWattmeterData", "type": null}}, "rfid": {".class": "SymbolTableNode", "implicit": true, "kind": "Mdef", "node": {".class": "Var", "flags": [], "fullname": "modbusSlave.ModbusSlave.rfid", "name": "rfid", "type": {".class": "AnyType", "missing_import_name": null, "source_any": null, "type_of_any": 1}}}, "run": {".class": "SymbolTableNode", "kind": "Mdef", "node": {".class": "FuncDef", "arg_kinds": [0], "arg_names": ["self"], "flags": ["is_coroutine"], "fullname": "modbusSlave.ModbusSlave.run", "name": "run", "type": null}}, "sreader": {".class": "SymbolTableNode", "implicit": true, "kind": "Mdef", "node": {".class": "Var", "flags": [], "fullname": "modbusSlave.ModbusSlave.sreader", "name": "sreader", "type": {".class": "AnyType", "missing_import_name": null, "source_any": null, "type_of_any": 1}}}, "swriter": {".class": "SymbolTableNode", "implicit": true, "kind": "Mdef", "node": {".class": "Var", "flags": [], "fullname": "modbusSlave.ModbusSlave.swriter", "name": "swriter", "type": {".class": "AnyType", "missing_import_name": null, "source_any": null, "type_of_any": 1}}}, "uart": {".class": "SymbolTableNode", "implicit": true, "kind": "Mdef", "node": {".class": "Var", "flags": [], "fullname": "modbusSlave.ModbusSlave.uart", "name": "uart", "type": {".class": "AnyType", "missing_import_name": null, "source_any": null, "type_of_any": 1}}}, "wattmeter": {".class": "SymbolTableNode", "implicit": true, "kind": "Mdef", "node": {".class": "Var", "flags": [], "fullname": "modbusSlave.ModbusSlave.wattmeter", "name": "wattmeter", "type": {".class": "AnyType", "missing_import_name": null, "source_any": null, "type_of_any": 1}}}}, "tuple_type": null, "type_vars": [], "typeddict_type": null}}, "Pin": {".class": "SymbolTableNode", "kind": "Gdef", "node": {".class": "Var", "flags": ["is_suppressed_import", "is_ready"], "fullname": "modbusSlave.Pin", "name": "Pin", "type": {".class": "AnyType", "missing_import_name": "modbusSlave.Pin", "source_any": null, "type_of_any": 3}}}, "UART": {".class": "SymbolTableNode", "kind": "Gdef", "node": {".class": "Var", "flags": ["is_suppressed_import", "is_ready"], "fullname": "modbusSlave.UART", "name": "UART", "type": {".class": "AnyType", "missing_import_name": "modbusSlave.UART", "source_any": null, "type_of_any": 3}}}, "__doc__": {".class": "SymbolTableNode", "kind": "Gdef", "node": {".class": "Var", "flags": ["is_ready"], "fullname": "modbusSlave.__doc__", "name": "__doc__", "type": "builtins.str"}}, "__file__": {".class": "SymbolTableNode", "kind": "Gdef", "node": {".class": "Var", "flags": ["is_ready"], "fullname": "modbusSlave.__file__", "name": "__file__", "type": "builtins.str"}}, "__name__": {".class": "SymbolTableNode", "kind": "Gdef", "node": {".class": "Var", "flags": ["is_ready"], "fullname": "modbusSlave.__name__", "name": "__name__", "type": "builtins.str"}}, "__package__": {".class": "SymbolTableNode", "kind": "Gdef", "node": {".class": "Var", "flags": ["is_ready"], "fullname": "modbusSlave.__package__", "name": "__package__", "type": "builtins.str"}}, "asyncio": {".class": "SymbolTableNode", "kind": "Gdef", "node": {".class": "Var", "flags": ["is_suppressed_import", "is_ready"], "fullname": "modbusSlave.asyncio", "name": "asyncio", "type": {".class": "AnyType", "missing_import_name": "modbusSlave.asyncio", "source_any": null, "type_of_any": 3}}}, "badDataLengthError": {".class": "SymbolTableNode", "kind": "Gdef", "node": {".class": "TypeInfo", "_promote": null, "abstract_attributes": [], "bases": ["builtins.ValueError"], "declared_metaclass": null, "defn": {".class": "ClassDef", "fullname": "modbusSlave.badDataLengthError", "name": "badDataLengthError", "type_vars": []}, "flags": [], "fullname": "modbusSlave.badDataLengthError", "metaclass_type": null, "metadata": {}, "module_name": "modbusSlave", "mro": ["modbusSlave.badDataLengthError", "builtins.ValueError", "builtins.Exception", "builtins.BaseException", "builtins.object"], "names": {".class": "SymbolTable"}, "tuple_type": null, "type_vars": [], "typeddict_type": null}}, "badFceError": {".class": "SymbolTableNode", "kind": "Gdef", "node": {".class": "TypeInfo", "_promote": null, "abstract_attributes": [], "bases": ["builtins.ValueError"], "declared_metaclass": null, "defn": {".class": "ClassDef", "fullname": "modbusSlave.badFceError", "name": "badFceError", "type_vars": []}, "flags": [], "fullname": "modbusSlave.badFceError", "metaclass_type": null, "metadata": {}, "module_name": "modbusSlave", "mro": ["modbusSlave.badFceError", "builtins.ValueError", "builtins.Exception", "builtins.BaseException", "builtins.object"], "names": {".class": "SymbolTable"}, "tuple_type": null, "type_vars": [], "typeddict_type": null}}, "badIDError": {".class": "SymbolTableNode", "kind": "Gdef", "node": {".class": "TypeInfo", "_promote": null, "abstract_attributes": [], "bases": ["builtins.ValueError"], "declared_metaclass": null, "defn": {".class": "ClassDef", "fullname": "modbusSlave.badIDError", "name": "badIDError", "type_vars": []}, "flags": [], "fullname": "modbusSlave.badIDError", "metaclass_type": null, "metadata": {}, "module_name": "modbusSlave", "mro": ["modbusSlave.badIDError", "builtins.ValueError", "builtins.Exception", "builtins.BaseException", "builtins.object"], "names": {".class": "SymbolTable"}, "tuple_type": null, "type_vars": [], "typeddict_type": null}}, "logging": {".class": "SymbolTableNode", "kind": "Gdef", "node": {".class": "Var", "flags": ["is_suppressed_import", "is_ready"], "fullname": "modbusSlave.logging", "name": "logging", "type": {".class": "AnyType", "missing_import_name": "modbusSlave.logging", "source_any": null, "type_of_any": 3}}}, "modbus": {".class": "SymbolTableNode", "kind": "Gdef", "node": {".class": "Var", "flags": ["is_suppressed_import", "is_ready"], "fullname": "modbusSlave.modbus", "name": "modbus", "type": {".class": "AnyType", "missing_import_name": "modbusSlave.modbus", "source_any": null, "type_of_any": 3}}}, "select": {".class": "SymbolTableNode", "kind": "Gdef", "node": {".class": "Var", "flags": ["is_suppressed_import", "is_ready"], "fullname": "modbusSlave.select", "name": "select", "type": {".class": "AnyType", "missing_import_name": "modbusSlave.select", "source_any": null, "type_of_any": 3}}}, "sleep": {".class": "SymbolTableNode", "cross_ref": "time.sleep", "kind": "Gdef"}}, "path": "/home/lipic/ME/SmartModul/smartmodule_tst_RAW/main/modbusSlave.py"}